Workbook

Sheet MAYOR
A1: fecha | B1: cuenta | C1: nombre_cuenta | D1: tercero | E1: valor
A2: 46208 | B2: 4135 | C2: Comercio al por mayor | D2: Panaderia El Trigal | E2: 45000000
A3: 46217 | B3: 4135 | C3: Comercio al por mayor | D3: Distribuciones Munoz | E3: 38000000
A4: 46231 | B4: 4135 | C4: Comercio al por mayor | D4: Cafeteria La Esquina | E4: 22000000
A5: 46233 | B5: 4175 | C5: Devoluciones en ventas | D5: Panaderia El Trigal | E5: -2000000
A6: 46234 | B6: 6135 | C6: Costo de ventas | D6: Varios | E6: -63000000
A7: 46234 | B7: 5105 | C7: Gastos de personal administracion | D7: Nomina | E7: -12000000
A8: 46234 | B8: 5205 | C8: Gastos de personal ventas | D8: Nomina | E8: -8000000
A9: 46213 | B9: 5110 | C9: Honorarios | D9: Contador Externo | E9: -2500000
A10: 46204 | B10: 5120 | C10: Arrendamientos | D10: Inmobiliaria Andes | E10: -4000000
A11: 46223 | B11: 5135 | C11: Servicios | D11: Empresas Publicas | E11: -1800000
A12: 46234 | B12: 5160 | C12: Depreciaciones | D12: Ajuste mensual | E12: -3000000
A13: 46234 | B13: 5305 | C13: Gastos financieros | D13: Banco Bogota | E13: -2200000
... A40: 46290 | B40: 2205 | C40: Proveedores nacionales | D40: Varios | E40: -20000000
D41: TOTAL | E41: =SUM(E2:E40) -> -6150000
D42: PYL | E42: =E41-E27-E40 -> 28850000

Sheet PYG
B1: Julio | C1: Agosto | D1: Septiembre | E1: Trimestre | G1: FECHA INICIO | H1: 46204 | I1: 46235 | J1: 46266
A2: Ingresos operacionales | B2: =SUMIFS(MAYOR!$E$2:$E$40,MAYOR!$B$2:$B$40,"4135",MAYOR!$A$2:$A$40,">="&H$1,MAYOR!$A$2:$A$40,"<="&H$2) -> 105000000 | C2: =SUMIFS(MAYOR!$E$2:$E$40,MAYOR!$B$2:$B$40,"4135",MAYOR!$A$2:$A$40,">="&I$1,MAYOR!$A$2:$A$40,"<="&I$2) -> 120000000 | D2: =SUMIFS(MAYOR!$E$2:$E$40,MAYOR!$B$2:$B$40,"4135",MAYOR!$A$2:$A$40,">="&J$1,MAYOR!$A$2:$A$40,"<="&J$2) -> 108000000 | E2: =SUM(B2:D2) -> 333000000 | G2: FECHA FINAL | H2: 46234 | I2: 46265 | J2: 46295
A3: Devoluciones en ventas | B3: =SUMIFS(MAYOR!$E$2:$E$40,MAYOR!$B$2:$B$40,"4175",MAYOR!$A$2:$A$40,">="&H$1,MAYOR!A3:A41,"<="&H$2) -> -2000000 | C3: =SUMIFS(MAYOR!$E$2:$E$40,MAYOR!$B$2:$B$40,"4175",MAYOR!$A$2:$A$40,">="&I$1,MAYOR!$A$3:$A$41,"<="&I$2) -> -3500000 | D3: =SUMIFS(MAYOR!$E$2:$E$40,MAYOR!$B$2:$B$40,"4175",MAYOR!$A$2:$A$40,">="&J$1,MAYOR!$A$3:$A$41,"<="&J$2) -> -1200000 | E3: =SUM(B3:D3) -> -6700000
A4: Ingresos netos | B4: =B2+B3 -> 103000000 | C4: =C2+C3 -> 116500000 | D4: =D2+D3 -> 106800000 | E4: =E2+E3 -> 326300000
A5: Costo de ventas | B5: =SUMIFS(MAYOR!E2:E40,MAYOR!B2:B40,"6135",MAYOR!A2:A40,">="&H1,MAYOR!A2:A40,"<="&H2) -> -63000000 | C5: =SUMIFS(MAYOR!$E$2:$E$40,MAYOR!$B$2:$B$40,"6135",MAYOR!$A$2:$A$40,">="&I$1,MAYOR!$A$2:$A$40,"<="&I$2) -> -68000000 | D5: =SUMIFS(MAYOR!$E$2:$E$40,MAYOR!$B$2:$B$40,"6135",MAYOR!$A$2:$A$40,">="&J$1,MAYOR!$A$2:$A$40,"<="&J$2) -> -64000000 | E5: =SUM(B5:D5) -> -195000000
A6: UTILIDAD BRUTA | B6: =B4+B5 -> 40000000 | C6: =C4+C5 -> 48500000 | D6: =D4+D5 -> 42800000 | E6: =E4+E5 -> 131300000
A7: Gastos de administración | B7: =SUMIFS(MAYOR!$E$2:$E$40,MAYOR!$B$2:$B$40,5105,MAYOR!$A$2:$A$40,">="&H$1,MAYOR!$A$2:$A$40,"<="&H$2)+SUMIFS(MAYOR!$E$2:$E$40,MAYOR!$B$2:$B$40,5110,MAYOR!$A$2:$A$40,">="&H$1,MAYOR!$A$2:$A$40,"<="&H$2)+SUMIFS(MAYOR!$E$2:$E$40,MAYOR!$B$2:$B$40,5120,MAYOR!$A$2:$A$40,">="&H$1,MAYOR!$A$2:$A$40,"<="&H$2)+SUMIFS(MAYOR!$E$2:$E$40,MAYOR!$B$2:$B$40,5135,MAYOR!$A$2:$A$40,">="&H$1,MAYOR!$A$2:$A$40,"<="&H$2)+SUMIFS(MAYOR!$E$2:$E$40,MAYOR!$B$2:$B$40,5160,MAYOR!$A$2:$A$40,">="&H$1,MAYOR!$A$2:$A$40,"<="&H$2) -> -23300000 | C7: =SUMIFS(MAYOR!$E$2:$E$40,MAYOR!$B$2:$B$40,5105,MAYOR!$A$2:$A$40,">="&I$1,MAYOR!$A$2:$A$40,"<="&I$2)+SUMIFS(MAYOR!$E$2:$E$40,MAYOR!$B$2:$B$40,5110,MAYOR!$A$2:$A$40,">="&I$1,MAYOR!$A$2:$A$40,"<="&I$2)+SUMIFS(MAYOR!$E$2:$E$40,MAYOR!$B$2:$B$40,5120,MAYOR!$A$2:$A$40,">="&I$1,MAYOR!$A$2:$A$40,"<="&I$2)+SUMIFS(MAYOR!$E$2:$E$40,MAYOR!$B$2:$B$40,5135,MAYOR!$A$2:$A$40,">="&I$1,MAYOR!$A$2:$A$40,"<="&I$2)+SUMIFS(MAYOR!$E$2:$E$40,MAYOR!$B$2:$B$40,5160,MAYOR!$A$2:$A$40,">="&I$1,MAYOR!$A$2:$A$40,"<="&I$2) -> -23600000 | D7: =SUMIFS(MAYOR!$E$2:$E$40,MAYOR!$B$2:$B$40,5105,MAYOR!$A$2:$A$40,">="&J$1,MAYOR!$A$2:$A$40,"<="&J$2)+SUMIFS(MAYOR!$E$2:$E$40,MAYOR!$B$2:$B$40,5110,MAYOR!$A$2:$A$40,">="&J$1,MAYOR!$A$2:$A$40,"<="&J$2)+SUMIFS(MAYOR!$E$2:$E$40,MAYOR!$B$2:$B$40,5120,MAYOR!$A$2:$A$40,">="&J$1,MAYOR!$A$2:$A$40,"<="&J$2)+SUMIFS(MAYOR!$E$2:$E$40,MAYOR!$B$2:$B$40,5135,MAYOR!$A$2:$A$40,">="&J$1,MAYOR!$A$2:$A$40,"<="&J$2)+SUMIFS(MAYOR!$E$2:$E$40,MAYOR!$B$2:$B$40,5160,MAYOR!$A$2:$A$40,">="&J$1,MAYOR!$A$2:$A$40,"<="&J$2) -> -23950000 | E7: =SUM(B7:D7) -> -70850000
A8: Gastos de ventas | B8: =SUMIFS(MAYOR!$E$2:$E$40,MAYOR!$B$2:$B$40,5205,MAYOR!$A$2:$A$40,">="&H1,MAYOR!$A$2:$A$40,"<="&H2) -> -8000000 | C8: =SUMIFS(MAYOR!$E$2:$E$40,MAYOR!$B$2:$B$40,5205,MAYOR!$A$2:$A$40,">="&I1,MAYOR!$A$2:$A$40,"<="&I2) -> -8000000 | D8: =SUMIFS(MAYOR!$E$2:$E$40,MAYOR!$B$2:$B$40,5205,MAYOR!$A$2:$A$40,">="&J1,MAYOR!$A$2:$A$40,"<="&J2) -> -8400000 | E8: =SUM(B8:D8) -> -24400000
A9: UTILIDAD OPERACIONAL | B9: =B6+B7+B8 -> 8700000 | C9: =C6+C7+C8 -> 16900000 | D9: =D6+D7+D8 -> 10450000 | E9: =E6+E7+E8 -> 36050000
A10: Gastos financieros | B10: =SUMIFS(MAYOR!$E$2:$E$40,MAYOR!$B$2:$B$40,5305,MAYOR!$A$2:$A$40,">="&H1,MAYOR!$A$2:$A$40,"<="&H2) -> -2200000 | C10: =SUMIFS(MAYOR!$E$2:$E$40,MAYOR!$B$2:$B$40,5305,MAYOR!$A$2:$A$40,">="&I1,MAYOR!$A$2:$A$40,"<="&I2) -> -2400000 | D10: =SUMIFS(MAYOR!$E$2:$E$40,MAYOR!$B$2:$B$40,5305,MAYOR!$A$2:$A$40,">="&J1,MAYOR!$A$2:$A$40,"<="&J2) -> -2600000 | E10: =SUM(B10:D10) -> -7200000
A11: UTILIDAD NETA | B11: =B9+B10 -> 6500000 | C11: =C9+C10 -> 14500000 | D11: =D9+D10 -> 7850000 | E11: =E9+E10 -> 28850000
D12: MAYOR | E12: =MAYOR!E42 -> 28850000 | F12: =E11-E12 -> 0 | G12: DIFERENCIA
